n8cog/__init__.py
n8cog/cog.py
n8cog/dm_configuration.py
n8cog-0.2.4.dist-info/LICENSE
n8cog-0.2.4.dist-info/METADATA
n8cog-0.2.4.dist-info/WHEEL
n8cog-0.2.4.dist-info/top_level.txt
n8cog-0.2.4.dist-info/RECORD
