Metadata-Version: 2.1
Name: n8cog
Version: 0.2.4
Summary: The base of all nwithan8 RedBot cogs
Home-page: https://github.com/nwithan8/n8cog
Author: Nate Harris
Author-email: n8gr8gbln@gmail.com
License: GNU General Public License v3 (GPLv3)
Download-URL: https://github.com/nwithan8/n8cog/archive/refs/tags/0.2.4.tar.gz
Keywords: red,redbot,cogs,n8cog,nwithan8
Platform: UNKNOWN
Classifier: License :: OSI Approved :: GNU General Public License v3 (GPLv3)
Classifier: Development Status :: 4 - Beta
Classifier: Intended Audience :: Developers
Classifier: Topic :: Software Development :: Build Tools
Classifier: Programming Language :: Python :: 3
Classifier: Programming Language :: Python :: 3.8
Classifier: Programming Language :: Python :: 3.9
Classifier: Programming Language :: Python :: 3.10
Classifier: Topic :: Multimedia
Classifier: Topic :: Internet :: WWW/HTTP
Classifier: Operating System :: OS Independent
Requires-Python: >=3.8, <4
License-File: LICENSE
Requires-Dist: Red-DiscordBot
Requires-Dist: questionflow (==0.2.2)
